perdoo/__init__.py
perdoo/__main__.py
perdoo/comic.py
perdoo/console.py
perdoo/settings.py
perdoo/utils.py
perdoo/cli/__init__.py
perdoo/cli/archive.py
perdoo/cli/settings.py
perdoo/metadata/__init__.py
perdoo/metadata/_base.py
perdoo/metadata/comic_info.py
perdoo/metadata/metron_info.py
perdoo/services/__init__.py
perdoo/services/_base.py
perdoo/services/comicvine.py
perdoo/services/metron.py
perdoo-0.8.0.dist-info/METADATA
perdoo-0.8.0.dist-info/WHEEL
perdoo-0.8.0.dist-info/entry_points.txt
perdoo-0.8.0.dist-info/licenses/LICENSE
perdoo-0.8.0.dist-info/RECORD
