Metadata-Version: 2.4
Name: perdoo
Version: 0.8.0
Summary: Unify and organize your comic collection.
Project-URL: Homepage, https://pypi.org/project/Perdoo
Project-URL: Issues, https://github.com/Buried-In-Code/Perdoo/issues
Project-URL: Source, https://github.com/Buried-In-Code/Perdoo
Author-email: BuriedInCode <BuriedInCode@tuta.io>
License-Expression: MIT
License-File: LICENSE
Keywords: comic,comics,metadata,tagger,tagging
Classifier: Development Status :: 4 - Beta
Classifier: Environment :: Console
Classifier: Framework :: Pydantic :: 2
Classifier: Intended Audience :: End Users/Desktop
Classifier: Natural Language :: English
Classifier: Operating System :: OS Independent
Classifier: Programming Language :: Python :: 3.10
Classifier: Programming Language :: Python :: 3.11
Classifier: Programming Language :: Python :: 3.12
Classifier: Programming Language :: Python :: 3.13
Classifier: Programming Language :: Python :: 3.14
Classifier: Typing :: Typed
Requires-Python: >=3.10
Requires-Dist: comicfn2dict>=0.2.0
Requires-Dist: darkseid>=7.1.0
Requires-Dist: lxml>=6.0.0
Requires-Dist: mokkari>=3.14.0
Requires-Dist: natsort>=8.4.0
Requires-Dist: pillow>=12.0.0
Requires-Dist: pydantic-xml>=2.18.0
Requires-Dist: pydantic>=2.12.0
Requires-Dist: questionary>=2.1.0
Requires-Dist: rich>=14.2.0
Requires-Dist: simyan>=1.6.0
Requires-Dist: tomli-w>=1.2.0
Requires-Dist: tomli>=2.3.0; python_version < '3.11'
Requires-Dist: typer>=0.20.0
Provides-Extra: cb7
Requires-Dist: darkseid[7zip]>=7.1.0; extra == 'cb7'
